{
  "hash": "7c28095a",
  "configHash": "fa96a80b",
  "lockfileHash": "152aa7ee",
  "browserHash": "129760ed",
  "optimized": {
    "react": {
      "src": "../../node_modules/react/index.js",
      "file": "react.js",
      "fileHash": "d20c66bc",
      "needsInterop": true
    },
    "react-dom/client": {
      "src": "../../node_modules/react-dom/client.js",
      "file": "react-dom_client.js",
      "fileHash": "ee8e9be8",
      "needsInterop": true
    }
  },
  "chunks": {
    "chunk-GFWMZNU4": {
      "file": "chunk-GFWMZNU4.js"
    }
  }
}